{
  "name": "Kepler-899 - System",
  "description": "Kepler-899 is a Sun-like G/F-type star with 1 known planet. Planet positions and surfaces are procedurally generated. Data from the NASA Exoplanet Archive.",
  "playing": false,
  "isLoaded": false,
  "elapsedTime": 0,
  "collisions": true,
  "massBeingModified": {
    "name": "Kepler-899",
    "unitName": "Solar Units",
    "unitMassQuantity": 0.93,
    "m": 0.93
  },
  "category": {
    "name": "Exoplanets",
    "subCategory": "1-Planet System"
  },
  "camera": {
    "cameraFocus": "Kepler-899",
    "logarithmicDepthBuffer": false,
    "rotatingReferenceFrame": "Kepler-899"
  },
  "integrator": {
    "name": "RK4",
    "g": 39.5,
    "dt": 0.00005,
    "tol": 0.0001,
    "maxDt": 0.001,
    "minDt": 0.000001,
    "useBarnesHut": false,
    "theta": 0.5,
    "softeningConstant": 0
  },
  "barycenter": {
    "display": false,
    "barycenterMassOne": "Kepler-899",
    "barycenterMassTwo": "Kepler-899 b",
    "systemBarycenter": true
  },
  "graphics": {
    "background": true,
    "orbits": true,
    "habitableZone": true,
    "trails": true,
    "labels": true
  },
  "masses": [
    {
      "name": "Kepler-899",
      "type": "star",
      "m": 0.93,
      "radius": 9345.7,
      "tilt": 0,
      "temperature": 5595,
      "graphics": {
        "orbit": true,
        "trail": true,
        "label": true
      },
      "elements": {
        "a": 0,
        "e": 0,
        "i": 0,
        "argP": 0,
        "lAn": 0,
        "eccAnom": 0
      },
      "position": {
        "x": 0,
        "y": 0,
        "z": 0
      },
      "velocity": {
        "x": 0,
        "y": -0.0004007362497299712,
        "z": -0.000021001696926562014
      },
      "nonStellarProceduralManifestation": false
    },
    {
      "name": "Kepler-899 b",
      "type": "sub-Neptune",
      "m": 0.00002297295,
      "radius": 251.9438,
      "tilt": 0,
      "graphics": {
        "orbit": true,
        "trail": true,
        "label": true
      },
      "elements": {
        "a": 0,
        "e": 0,
        "i": 0,
        "argP": 0,
        "lAn": 0,
        "trueAnom": 0,
        "eccAnom": 0,
        "meanAnom": 0
      },
      "position": {
        "x": 0.1392,
        "y": 0,
        "z": 0
      },
      "velocity": {
        "x": 0,
        "y": 16.222762520654648,
        "z": 0.850198957543662
      },
      "nonStellarProceduralManifestation": true,
      "atmosphere": "beige"
    }
  ],
  "particlesConfiguration": {
    "max": 50000,
    "softening": 0,
    "size": 80,
    "shapes": []
  },
  "ringToBeAdded": {
    "primary": "Kepler-899",
    "a": 0,
    "aInterval": 0,
    "i": 0,
    "lAn": 0,
    "number": 1000,
    "size": 0,
    "ringsAreBeingAdded": false
  }
}
