{
  "name": "Kepler-178 - System",
  "description": "Kepler-178 is a Sun-like G/F-type star with 3 known planets. Planet positions and surfaces are procedurally generated. Data from the NASA Exoplanet Archive.",
  "playing": false,
  "isLoaded": false,
  "elapsedTime": 0,
  "collisions": true,
  "massBeingModified": {
    "name": "Kepler-178",
    "unitName": "Solar Units",
    "unitMassQuantity": 0.852,
    "m": 0.852
  },
  "category": {
    "name": "Exoplanets",
    "subCategory": "3-Planet System"
  },
  "camera": {
    "cameraFocus": "Kepler-178",
    "logarithmicDepthBuffer": false,
    "rotatingReferenceFrame": "Kepler-178"
  },
  "integrator": {
    "name": "RK4",
    "g": 39.5,
    "dt": 2e-5,
    "tol": 0.001,
    "maxDt": 0.0001,
    "minDt": 2e-6,
    "useBarnesHut": false,
    "theta": 0.5,
    "softeningConstant": 0
  },
  "barycenter": {
    "display": false,
    "barycenterMassOne": "Kepler-178",
    "barycenterMassTwo": "Kepler-178 b",
    "systemBarycenter": true
  },
  "graphics": {
    "background": true,
    "orbits": true,
    "habitableZone": true,
    "trails": true,
    "labels": true
  },
  "masses": [
    {
      "name": "Kepler-178",
      "type": "star",
      "m": 0.852,
      "radius": 10947.82,
      "tilt": 0,
      "temperature": 5676,
      "graphics": {
        "orbit": true,
        "trail": true,
        "label": true
      },
      "elements": {
        "a": 0,
        "e": 0,
        "i": 0,
        "argP": 0,
        "lAn": 0,
        "eccAnom": 0
      },
      "position": {
        "x": 0.0,
        "y": 0.0,
        "z": 0.0
      },
      "velocity": {
        "x": -9.449869820404043e-6,
        "y": -0.00013865327251317235,
        "z": -8.181750607780253e-5
      },
      "nonStellarProceduralManifestation": false
    },
    {
      "name": "Kepler-178 b",
      "type": "sub-Neptune",
      "m": 2.6276249999999998e-5,
      "radius": 272.6257,
      "tilt": 0,
      "graphics": {
        "orbit": true,
        "trail": true,
        "label": true
      },
      "elements": {
        "a": 0,
        "e": 0,
        "i": 0,
        "argP": 0,
        "lAn": 0,
        "trueAnom": 0,
        "eccAnom": 0,
        "meanAnom": 0
      },
      "position": {
        "x": 0.085,
        "y": 0.0,
        "z": 0.0
      },
      "velocity": {
        "x": -0.0,
        "y": 19.870705583659912,
        "z": 1.0413795524267433
      },
      "nonStellarProceduralManifestation": true,
      "atmosphere": "beige"
    },
    {
      "name": "Kepler-178 c",
      "type": "sub-Neptune",
      "m": 2.597595e-5,
      "radius": 270.7455,
      "tilt": 0,
      "graphics": {
        "orbit": true,
        "trail": true,
        "label": true
      },
      "elements": {
        "a": 0,
        "e": 0,
        "i": 0,
        "argP": 0,
        "lAn": 0,
        "trueAnom": 0,
        "eccAnom": 0,
        "meanAnom": 0
      },
      "position": {
        "x": -0.07099999999999997,
        "y": 0.1229756073373903,
        "z": 0.0
      },
      "velocity": {
        "x": -13.314020183658103,
        "y": -7.686853137031112,
        "z": 0.8057018051733592
      },
      "nonStellarProceduralManifestation": true,
      "atmosphere": "beige"
    },
    {
      "name": "Kepler-178 d",
      "type": "sub-Neptune",
      "m": 4.44444e-5,
      "radius": 371.335,
      "tilt": 0,
      "graphics": {
        "orbit": true,
        "trail": true,
        "label": true
      },
      "elements": {
        "a": 0,
        "e": 0,
        "i": 0,
        "argP": 0,
        "lAn": 0,
        "trueAnom": 0,
        "eccAnom": 0,
        "meanAnom": 0
      },
      "position": {
        "x": -0.19850000000000018,
        "y": -0.3438120853024221,
        "z": 0.0
      },
      "velocity": {
        "x": 7.9626592253844795,
        "y": -4.597243447240992,
        "z": 0.4818626397868264
      },
      "nonStellarProceduralManifestation": true,
      "atmosphere": "beige"
    }
  ],
  "particlesConfiguration": {
    "max": 50000,
    "softening": 0,
    "size": 80,
    "shapes": []
  },
  "ringToBeAdded": {
    "primary": "Kepler-178",
    "a": 0,
    "aInterval": 0,
    "i": 0,
    "lAn": 0,
    "number": 1000,
    "size": 0,
    "ringsAreBeingAdded": false
  }
}
