{
  "name": "HD 74698 - System",
  "description": "HD 74698 is a Sun-like G/F-type star with 2 known planets. Planet positions and surfaces are procedurally generated. Data from the NASA Exoplanet Archive.",
  "playing": false,
  "isLoaded": false,
  "elapsedTime": 0,
  "collisions": true,
  "massBeingModified": {
    "name": "HD 74698",
    "unitName": "Solar Units",
    "unitMassQuantity": 1.039,
    "m": 1.039
  },
  "category": {
    "name": "Exoplanets",
    "subCategory": "2-Planet System"
  },
  "camera": {
    "cameraFocus": "HD 74698",
    "logarithmicDepthBuffer": false,
    "rotatingReferenceFrame": "HD 74698"
  },
  "integrator": {
    "name": "PEFRL",
    "g": 39.5,
    "dt": 0.0005,
    "tol": 0.0001,
    "maxDt": 0.01,
    "minDt": 0.00001,
    "useBarnesHut": false,
    "theta": 0.5,
    "softeningConstant": 0
  },
  "barycenter": {
    "display": false,
    "barycenterMassOne": "HD 74698",
    "barycenterMassTwo": "HD 74698 b",
    "systemBarycenter": true
  },
  "graphics": {
    "background": true,
    "orbits": true,
    "habitableZone": true,
    "trails": true,
    "labels": true
  },
  "masses": [
    {
      "name": "HD 74698",
      "type": "star",
      "m": 1.039,
      "radius": 13689.91,
      "tilt": 0,
      "temperature": 5783,
      "graphics": {
        "orbit": true,
        "trail": true,
        "label": true
      },
      "elements": {
        "a": 0,
        "e": 0,
        "i": 0,
        "argP": 0,
        "lAn": 0,
        "eccAnom": 0
      },
      "position": {
        "x": 0,
        "y": 0,
        "z": 0
      },
      "velocity": {
        "x": -0.0004978884651232742,
        "y": 0.0007768812495295862,
        "z": 0.00007243031486036321
      },
      "nonStellarProceduralManifestation": false
    },
    {
      "name": "HD 74698 b",
      "type": "gas giant planet",
      "m": 0.000069069,
      "radius": 481.3254,
      "tilt": 0,
      "graphics": {
        "orbit": true,
        "trail": true,
        "label": true
      },
      "elements": {
        "a": 0,
        "e": 0,
        "i": 0,
        "argP": 0,
        "lAn": 0,
        "trueAnom": 0,
        "eccAnom": 0,
        "meanAnom": 0
      },
      "position": {
        "x": -0.0869714070441502,
        "y": 0.0654478389414142,
        "z": 0.003429975897793665
      },
      "velocity": {
        "x": -12.25326283048279,
        "y": -16.238344360250384,
        "z": -0.8510155671540192
      },
      "nonStellarProceduralManifestation": true,
      "atmosphere": "beige"
    },
    {
      "name": "HD 74698 c",
      "type": "gas giant planet",
      "m": 0.00037837799999999996,
      "radius": 1316.1241,
      "tilt": 0,
      "graphics": {
        "orbit": true,
        "trail": true,
        "label": true
      },
      "elements": {
        "a": 0,
        "e": 0,
        "i": 0,
        "argP": 0,
        "lAn": 0,
        "trueAnom": 0,
        "eccAnom": 0,
        "meanAnom": 0
      },
      "position": {
        "x": 0.8098237956379137,
        "y": -3.502925008110948,
        "z": 0.18358052067012393
      },
      "velocity": {
        "x": 3.603874236085866,
        "y": 0.8308796715371762,
        "z": -0.04354455843668613
      },
      "nonStellarProceduralManifestation": true,
      "atmosphere": "lightcyan"
    }
  ],
  "particlesConfiguration": {
    "max": 50000,
    "softening": 0,
    "size": 80,
    "shapes": []
  },
  "ringToBeAdded": {
    "primary": "HD 74698",
    "a": 0,
    "aInterval": 0,
    "i": 0,
    "lAn": 0,
    "number": 1000,
    "size": 0,
    "ringsAreBeingAdded": false
  }
}
