{
  "name": "TOI-2088 - System",
  "description": "TOI-2088 is a orange K-type dwarf star with 1 known planet. Planet positions and surfaces are procedurally generated. Data from the NASA Exoplanet Archive.",
  "playing": false,
  "isLoaded": false,
  "elapsedTime": 0,
  "collisions": true,
  "massBeingModified": {
    "name": "TOI-2088",
    "unitName": "Solar Units",
    "unitMassQuantity": 0.9027,
    "m": 0.9027
  },
  "category": {
    "name": "Exoplanets",
    "subCategory": "1-Planet System"
  },
  "camera": {
    "cameraFocus": "TOI-2088",
    "logarithmicDepthBuffer": false,
    "rotatingReferenceFrame": "TOI-2088"
  },
  "integrator": {
    "name": "RK4",
    "g": 39.5,
    "dt": 0.0001,
    "tol": 0.0001,
    "maxDt": 0.001,
    "minDt": 0.000001,
    "useBarnesHut": false,
    "theta": 0.5,
    "softeningConstant": 0
  },
  "barycenter": {
    "display": false,
    "barycenterMassOne": "TOI-2088",
    "barycenterMassTwo": "TOI-2088 b",
    "systemBarycenter": true
  },
  "graphics": {
    "background": true,
    "orbits": true,
    "habitableZone": true,
    "trails": true,
    "labels": true
  },
  "masses": [
    {
      "name": "TOI-2088",
      "type": "star",
      "m": 0.9027,
      "radius": 8709.987,
      "tilt": 0,
      "temperature": 5081,
      "graphics": {
        "orbit": true,
        "trail": true,
        "label": true
      },
      "elements": {
        "a": 0,
        "e": 0,
        "i": 0,
        "argP": 0,
        "lAn": 0,
        "eccAnom": 0
      },
      "position": {
        "x": 0,
        "y": 0,
        "z": 0
      },
      "velocity": {
        "x": 0.0010698253476484273,
        "y": -6.54181330691087e-20,
        "z": -3.428419078994467e-21
      },
      "nonStellarProceduralManifestation": false
    },
    {
      "name": "TOI-2088 b",
      "type": "sub-Neptune",
      "m": 0.000111111,
      "radius": 346.2457,
      "tilt": 0,
      "graphics": {
        "orbit": true,
        "trail": true,
        "label": true
      },
      "elements": {
        "a": 0,
        "e": 0,
        "i": 0,
        "argP": 0,
        "lAn": 0,
        "trueAnom": 0,
        "eccAnom": 0,
        "meanAnom": 0
      },
      "position": {
        "x": 2.8901664459877533e-17,
        "y": 0.4713531404041588,
        "z": 0.024702571346669488
      },
      "velocity": {
        "x": -8.691590763490881,
        "y": 5.314770699704297e-16,
        "z": 2.7853532977007726e-17
      },
      "nonStellarProceduralManifestation": true,
      "atmosphere": "beige"
    }
  ],
  "particlesConfiguration": {
    "max": 50000,
    "softening": 0,
    "size": 80,
    "shapes": []
  },
  "ringToBeAdded": {
    "primary": "TOI-2088",
    "a": 0,
    "aInterval": 0,
    "i": 0,
    "lAn": 0,
    "number": 1000,
    "size": 0,
    "ringsAreBeingAdded": false
  }
}
