{
  "name": "Kepler-595 - System",
  "description": "Kepler-595 is a orange K-type dwarf star with 2 known planets. Planet positions and surfaces are procedurally generated. Data from the NASA Exoplanet Archive.",
  "playing": false,
  "isLoaded": false,
  "elapsedTime": 0,
  "collisions": true,
  "massBeingModified": {
    "name": "Kepler-595",
    "unitName": "Solar Units",
    "unitMassQuantity": 0.93,
    "m": 0.93
  },
  "category": {
    "name": "Exoplanets",
    "subCategory": "2-Planet System"
  },
  "camera": {
    "cameraFocus": "Kepler-595",
    "logarithmicDepthBuffer": false,
    "rotatingReferenceFrame": "Kepler-595"
  },
  "integrator": {
    "name": "RK4",
    "g": 39.5,
    "dt": 2e-5,
    "tol": 0.001,
    "maxDt": 0.0001,
    "minDt": 2e-6,
    "useBarnesHut": false,
    "theta": 0.5,
    "softeningConstant": 0
  },
  "barycenter": {
    "display": false,
    "barycenterMassOne": "Kepler-595",
    "barycenterMassTwo": "Kepler-595 c",
    "systemBarycenter": true
  },
  "graphics": {
    "background": true,
    "orbits": true,
    "habitableZone": true,
    "trails": true,
    "labels": true
  },
  "masses": [
    {
      "name": "Kepler-595",
      "type": "star",
      "m": 0.93,
      "radius": 8431.67,
      "tilt": 0,
      "temperature": 5138,
      "graphics": {
        "orbit": true,
        "trail": true,
        "label": true
      },
      "elements": {
        "a": 0,
        "e": 0,
        "i": 0,
        "argP": 0,
        "lAn": 0,
        "eccAnom": 0
      },
      "position": {
        "x": 0.0,
        "y": 0.0,
        "z": 0.0
      },
      "velocity": {
        "x": 1.0470650715542427e-19,
        "y": 0.0006492841835285372,
        "z": -5.5589080672847836e-5
      },
      "nonStellarProceduralManifestation": false
    },
    {
      "name": "Kepler-595 c",
      "type": "terrestial planet",
      "m": 9.9099e-6,
      "radius": 94.8549,
      "tilt": 0,
      "graphics": {
        "orbit": true,
        "trail": true,
        "label": true
      },
      "elements": {
        "a": 0,
        "e": 0,
        "i": 0,
        "argP": 0,
        "lAn": 0,
        "trueAnom": 0,
        "eccAnom": 0,
        "meanAnom": 0
      },
      "position": {
        "x": 0.0983,
        "y": 0.0,
        "z": 0.0
      },
      "velocity": {
        "x": -0.0,
        "y": 19.30490503010915,
        "z": 1.0117272018980323
      },
      "nonStellarProceduralManifestation": true,
      "atmosphere": "orange"
    },
    {
      "name": "Kepler-595 b",
      "type": "sub-Neptune",
      "m": 5.2252199999999994e-5,
      "radius": 348.5849,
      "tilt": 0,
      "graphics": {
        "orbit": true,
        "trail": true,
        "label": true
      },
      "elements": {
        "a": 0,
        "e": 0,
        "i": 0,
        "argP": 0,
        "lAn": 0,
        "trueAnom": 0,
        "eccAnom": 0,
        "meanAnom": 0
      },
      "position": {
        "x": -0.1582,
        "y": 1.937391236251113e-17,
        "z": 0.0
      },
      "velocity": {
        "x": -1.863597162503102e-15,
        "y": -15.217425659386942,
        "z": 0.7975114852132387
      },
      "nonStellarProceduralManifestation": true,
      "atmosphere": "beige"
    }
  ],
  "particlesConfiguration": {
    "max": 50000,
    "softening": 0,
    "size": 80,
    "shapes": []
  },
  "ringToBeAdded": {
    "primary": "Kepler-595",
    "a": 0,
    "aInterval": 0,
    "i": 0,
    "lAn": 0,
    "number": 1000,
    "size": 0,
    "ringsAreBeingAdded": false
  }
}
