{
  "name": "Kepler-207 - System",
  "description": "Kepler-207 is a Sun-like G/F-type star with 3 known planets. Planet positions and surfaces are procedurally generated. Data from the NASA Exoplanet Archive.",
  "playing": false,
  "isLoaded": false,
  "elapsedTime": 0,
  "collisions": true,
  "massBeingModified": {
    "name": "Kepler-207",
    "unitName": "Solar Units",
    "unitMassQuantity": 1.313,
    "m": 1.313
  },
  "category": {
    "name": "Exoplanets",
    "subCategory": "3-Planet System"
  },
  "camera": {
    "cameraFocus": "Kepler-207",
    "logarithmicDepthBuffer": false,
    "rotatingReferenceFrame": "Kepler-207"
  },
  "integrator": {
    "name": "RK4",
    "g": 39.5,
    "dt": 5e-6,
    "tol": 0.001,
    "maxDt": 0.0001,
    "minDt": 5e-7,
    "useBarnesHut": false,
    "theta": 0.5,
    "softeningConstant": 0
  },
  "barycenter": {
    "display": false,
    "barycenterMassOne": "Kepler-207",
    "barycenterMassTwo": "Kepler-207 b",
    "systemBarycenter": true
  },
  "graphics": {
    "background": true,
    "orbits": true,
    "habitableZone": true,
    "trails": true,
    "labels": true
  },
  "masses": [
    {
      "name": "Kepler-207",
      "type": "star",
      "m": 1.313,
      "radius": 16308.76,
      "tilt": 0,
      "temperature": 5920,
      "graphics": {
        "orbit": true,
        "trail": true,
        "label": true
      },
      "elements": {
        "a": 0,
        "e": 0,
        "i": 0,
        "argP": 0,
        "lAn": 0,
        "eccAnom": 0
      },
      "position": {
        "x": 0.0,
        "y": 0.0,
        "z": 0.0
      },
      "velocity": {
        "x": -0.00040666870464719764,
        "y": 0.00016059791470100925,
        "z": -6.375795857419923e-5
      },
      "nonStellarProceduralManifestation": false
    },
    {
      "name": "Kepler-207 b",
      "type": "super-Earth",
      "m": 9.279269999999999e-6,
      "radius": 147.5939,
      "tilt": 0,
      "graphics": {
        "orbit": true,
        "trail": true,
        "label": true
      },
      "elements": {
        "a": 0,
        "e": 0,
        "i": 0,
        "argP": 0,
        "lAn": 0,
        "trueAnom": 0,
        "eccAnom": 0,
        "meanAnom": 0
      },
      "position": {
        "x": 0.029,
        "y": 0.0,
        "z": 0.0
      },
      "velocity": {
        "x": -0.0,
        "y": 42.231481622214666,
        "z": 2.213258167652837
      },
      "nonStellarProceduralManifestation": true,
      "atmosphere": "orange"
    },
    {
      "name": "Kepler-207 c",
      "type": "terrestial planet",
      "m": 8.58858e-6,
      "radius": 141.0133,
      "tilt": 0,
      "graphics": {
        "orbit": true,
        "trail": true,
        "label": true
      },
      "elements": {
        "a": 0,
        "e": 0,
        "i": 0,
        "argP": 0,
        "lAn": 0,
        "trueAnom": 0,
        "eccAnom": 0,
        "meanAnom": 0
      },
      "position": {
        "x": -0.02199999999999999,
        "y": 0.0381051177665153,
        "z": 0.0
      },
      "velocity": {
        "x": -29.692010851620957,
        "y": -17.142690457964637,
        "z": 1.7968206756770155
      },
      "nonStellarProceduralManifestation": true,
      "atmosphere": "orange"
    },
    {
      "name": "Kepler-207 d",
      "type": "sub-Neptune",
      "m": 3.3033e-5,
      "radius": 311.1693,
      "tilt": 0,
      "graphics": {
        "orbit": true,
        "trail": true,
        "label": true
      },
      "elements": {
        "a": 0,
        "e": 0,
        "i": 0,
        "argP": 0,
        "lAn": 0,
        "trueAnom": 0,
        "eccAnom": 0,
        "meanAnom": 0
      },
      "position": {
        "x": -0.03400000000000003,
        "y": -0.05888972745734181,
        "z": 0.0
      },
      "velocity": {
        "x": 23.884243627941306,
        "y": -13.789574487982534,
        "z": 1.445361952346488
      },
      "nonStellarProceduralManifestation": true,
      "atmosphere": "orange"
    }
  ],
  "particlesConfiguration": {
    "max": 50000,
    "softening": 0,
    "size": 80,
    "shapes": []
  },
  "ringToBeAdded": {
    "primary": "Kepler-207",
    "a": 0,
    "aInterval": 0,
    "i": 0,
    "lAn": 0,
    "number": 1000,
    "size": 0,
    "ringsAreBeingAdded": false
  }
}
