{
  "name": "Kepler-1338 - System",
  "description": "Kepler-1338 is a Sun-like G/F-type star with 1 known planet. Planet positions and surfaces are procedurally generated. Data from the NASA Exoplanet Archive.",
  "playing": false,
  "isLoaded": false,
  "elapsedTime": 0,
  "collisions": true,
  "massBeingModified": {
    "name": "Kepler-1338",
    "unitName": "Solar Units",
    "unitMassQuantity": 1.04,
    "m": 1.04
  },
  "category": {
    "name": "Exoplanets",
    "subCategory": "1-Planet System"
  },
  "camera": {
    "cameraFocus": "Kepler-1338",
    "logarithmicDepthBuffer": false,
    "rotatingReferenceFrame": "Kepler-1338"
  },
  "integrator": {
    "name": "RK4",
    "g": 39.5,
    "dt": 2e-6,
    "tol": 0.001,
    "maxDt": 0.0001,
    "minDt": 2e-7,
    "useBarnesHut": false,
    "theta": 0.5,
    "softeningConstant": 0
  },
  "barycenter": {
    "display": false,
    "barycenterMassOne": "Kepler-1338",
    "barycenterMassTwo": "Kepler-1338 b",
    "systemBarycenter": true
  },
  "graphics": {
    "background": true,
    "orbits": true,
    "habitableZone": true,
    "trails": true,
    "labels": true
  },
  "masses": [
    {
      "name": "Kepler-1338",
      "type": "star",
      "m": 1.04,
      "radius": 10783.5,
      "tilt": 0,
      "temperature": 5909,
      "graphics": {
        "orbit": true,
        "trail": true,
        "label": true
      },
      "elements": {
        "a": 0,
        "e": 0,
        "i": 0,
        "argP": 0,
        "lAn": 0,
        "eccAnom": 0
      },
      "position": {
        "x": 0.0,
        "y": 0.0,
        "z": 0.0
      },
      "velocity": {
        "x": -0.0,
        "y": -9.57441110017101e-5,
        "z": -5.0177362370286216e-6
      },
      "nonStellarProceduralManifestation": false
    },
    {
      "name": "Kepler-1338 b",
      "type": "terrestial planet",
      "m": 2.1651629999999997e-6,
      "radius": 86.4882,
      "tilt": 0,
      "graphics": {
        "orbit": true,
        "trail": true,
        "label": true
      },
      "elements": {
        "a": 0,
        "e": 0,
        "i": 0,
        "argP": 0,
        "lAn": 0,
        "trueAnom": 0,
        "eccAnom": 0,
        "meanAnom": 0
      },
      "position": {
        "x": 0.01937,
        "y": 0.0,
        "z": 0.0
      },
      "velocity": {
        "x": -0.0,
        "y": 45.98908970907896,
        "z": 2.410186062901392
      },
      "nonStellarProceduralManifestation": true,
      "atmosphere": "orange"
    }
  ],
  "particlesConfiguration": {
    "max": 50000,
    "softening": 0,
    "size": 80,
    "shapes": []
  },
  "ringToBeAdded": {
    "primary": "Kepler-1338",
    "a": 0,
    "aInterval": 0,
    "i": 0,
    "lAn": 0,
    "number": 1000,
    "size": 0,
    "ringsAreBeingAdded": false
  }
}
