{
  "name": "TOI-5573 - System",
  "description": "TOI-5573 is a orange K-type dwarf star with 1 known planet. Planet positions and surfaces are procedurally generated. Data from the NASA Exoplanet Archive.",
  "playing": false,
  "isLoaded": false,
  "elapsedTime": 0,
  "collisions": true,
  "massBeingModified": {
    "name": "TOI-5573",
    "unitName": "Solar Units",
    "unitMassQuantity": 0.619,
    "m": 0.619
  },
  "category": {
    "name": "Exoplanets",
    "subCategory": "1-Planet System"
  },
  "camera": {
    "cameraFocus": "TOI-5573",
    "logarithmicDepthBuffer": false,
    "rotatingReferenceFrame": "TOI-5573"
  },
  "integrator": {
    "name": "RK4",
    "g": 39.5,
    "dt": 2e-5,
    "tol": 0.001,
    "maxDt": 0.0001,
    "minDt": 2e-6,
    "useBarnesHut": false,
    "theta": 0.5,
    "softeningConstant": 0
  },
  "barycenter": {
    "display": false,
    "barycenterMassOne": "TOI-5573",
    "barycenterMassTwo": "TOI-5573 b",
    "systemBarycenter": true
  },
  "graphics": {
    "background": true,
    "orbits": true,
    "habitableZone": true,
    "trails": true,
    "labels": true
  },
  "masses": [
    {
      "name": "TOI-5573",
      "type": "star",
      "m": 0.619,
      "radius": 6100.38,
      "tilt": 0,
      "temperature": 3790,
      "graphics": {
        "orbit": true,
        "trail": true,
        "label": true
      },
      "elements": {
        "a": 0,
        "e": 0,
        "i": 0,
        "argP": 0,
        "lAn": 0,
        "eccAnom": 0
      },
      "position": {
        "x": 0.0,
        "y": 0.0,
        "z": 0.0
      },
      "velocity": {
        "x": 0.005862399408732575,
        "y": -0.00908419657189527,
        "z": -0.00047608256890364697
      },
      "nonStellarProceduralManifestation": false
    },
    {
      "name": "TOI-5573 b",
      "type": "gas giant planet",
      "m": 0.000336336,
      "radius": 916.5864,
      "tilt": 0,
      "graphics": {
        "orbit": true,
        "trail": true,
        "label": true
      },
      "elements": {
        "a": 0,
        "e": 0,
        "i": 0,
        "argP": 0,
        "lAn": 0,
        "trueAnom": 0,
        "eccAnom": 0,
        "meanAnom": 0
      },
      "position": {
        "x": 0.05553926153273245,
        "y": 0.03574355907269276,
        "z": 0.0018732405546720277
      },
      "velocity": {
        "x": -10.789285815391345,
        "y": 16.718750529242104,
        "z": 0.8761925876247486
      },
      "nonStellarProceduralManifestation": true,
      "atmosphere": "beige"
    }
  ],
  "particlesConfiguration": {
    "max": 50000,
    "softening": 0,
    "size": 80,
    "shapes": []
  },
  "ringToBeAdded": {
    "primary": "TOI-5573",
    "a": 0,
    "aInterval": 0,
    "i": 0,
    "lAn": 0,
    "number": 1000,
    "size": 0,
    "ringsAreBeingAdded": false
  }
}
