{
  "name": "TOI-6628 - System",
  "description": "TOI-6628 is a Sun-like G/F-type star with 1 known planet. Planet positions and surfaces are procedurally generated. Data from the NASA Exoplanet Archive.",
  "playing": false,
  "isLoaded": false,
  "elapsedTime": 0,
  "collisions": true,
  "massBeingModified": {
    "name": "TOI-6628",
    "unitName": "Solar Units",
    "unitMassQuantity": 0.97,
    "m": 0.97
  },
  "category": {
    "name": "Exoplanets",
    "subCategory": "1-Planet System"
  },
  "camera": {
    "cameraFocus": "TOI-6628",
    "logarithmicDepthBuffer": false,
    "rotatingReferenceFrame": "TOI-6628"
  },
  "integrator": {
    "name": "PEFRL",
    "g": 39.5,
    "dt": 0.0005,
    "tol": 0.0001,
    "maxDt": 0.01,
    "minDt": 0.00001,
    "useBarnesHut": false,
    "theta": 0.5,
    "softeningConstant": 0
  },
  "barycenter": {
    "display": false,
    "barycenterMassOne": "TOI-6628",
    "barycenterMassTwo": "TOI-6628 b",
    "systemBarycenter": true
  },
  "graphics": {
    "background": true,
    "orbits": true,
    "habitableZone": true,
    "trails": true,
    "labels": true
  },
  "masses": [
    {
      "name": "TOI-6628",
      "type": "star",
      "m": 0.97,
      "radius": 10372.7,
      "tilt": 0,
      "temperature": 5463,
      "graphics": {
        "orbit": true,
        "trail": true,
        "label": true
      },
      "elements": {
        "a": 0,
        "e": 0,
        "i": 0,
        "argP": 0,
        "lAn": 0,
        "eccAnom": 0
      },
      "position": {
        "x": 0,
        "y": 0,
        "z": 0
      },
      "velocity": {
        "x": -0.016201892778937518,
        "y": 0.022433691574643814,
        "z": 0.0011756999565477543
      },
      "nonStellarProceduralManifestation": false
    },
    {
      "name": "TOI-6628 b",
      "type": "gas giant planet",
      "m": 0.00070628464260354,
      "radius": 1032.6687,
      "tilt": 0,
      "graphics": {
        "orbit": true,
        "trail": true,
        "label": true
      },
      "elements": {
        "a": 0,
        "e": 0,
        "i": 0,
        "argP": 0,
        "lAn": 0,
        "trueAnom": 0,
        "eccAnom": 0,
        "meanAnom": 0
      },
      "position": {
        "x": -0.035865242075708015,
        "y": -0.0258313787986196,
        "z": -0.0013537651986546863
      },
      "velocity": {
        "x": 22.251419679234324,
        "y": -30.81007219297484,
        "z": -1.614687463183991
      },
      "nonStellarProceduralManifestation": true,
      "atmosphere": "beige"
    }
  ],
  "particlesConfiguration": {
    "max": 50000,
    "softening": 0,
    "size": 80,
    "shapes": []
  },
  "ringToBeAdded": {
    "primary": "TOI-6628",
    "a": 0,
    "aInterval": 0,
    "i": 0,
    "lAn": 0,
    "number": 1000,
    "size": 0,
    "ringsAreBeingAdded": false
  }
}
