{
  "name": "WASP-79 - System",
  "description": "WASP-79 is a Sun-like G/F-type star with 1 known planet. Planet positions and surfaces are procedurally generated. Data from the NASA Exoplanet Archive.",
  "playing": false,
  "isLoaded": false,
  "elapsedTime": 0,
  "collisions": true,
  "massBeingModified": {
    "name": "WASP-79",
    "unitName": "Solar Units",
    "unitMassQuantity": 1.39,
    "m": 1.39
  },
  "category": {
    "name": "Exoplanets",
    "subCategory": "1-Planet System"
  },
  "camera": {
    "cameraFocus": "WASP-79",
    "logarithmicDepthBuffer": false,
    "rotatingReferenceFrame": "WASP-79"
  },
  "integrator": {
    "name": "RK4",
    "g": 39.5,
    "dt": 1e-5,
    "tol": 0.001,
    "maxDt": 0.0001,
    "minDt": 1e-6,
    "useBarnesHut": false,
    "theta": 0.5,
    "softeningConstant": 0
  },
  "barycenter": {
    "display": false,
    "barycenterMassOne": "WASP-79",
    "barycenterMassTwo": "WASP-79 b",
    "systemBarycenter": true
  },
  "graphics": {
    "background": true,
    "orbits": true,
    "habitableZone": true,
    "trails": true,
    "labels": true
  },
  "masses": [
    {
      "name": "WASP-79",
      "type": "star",
      "m": 1.39,
      "radius": 15507.7,
      "tilt": 0,
      "temperature": 6600,
      "graphics": {
        "orbit": true,
        "trail": true,
        "label": true
      },
      "elements": {
        "a": 0,
        "e": 0,
        "i": 0,
        "argP": 0,
        "lAn": 0,
        "eccAnom": 0
      },
      "position": {
        "x": 0.0,
        "y": 0.0,
        "z": 0.0
      },
      "velocity": {
        "x": 0.018983419187513194,
        "y": -1.1608061495693006e-18,
        "z": -6.083527247702481e-20
      },
      "nonStellarProceduralManifestation": false
    },
    {
      "name": "WASP-79 b",
      "type": "gas giant planet",
      "m": 0.00081127290028785,
      "radius": 1612.2276,
      "tilt": 0,
      "graphics": {
        "orbit": true,
        "trail": true,
        "label": true
      },
      "elements": {
        "a": 0,
        "e": 0,
        "i": 0,
        "argP": 0,
        "lAn": 0,
        "trueAnom": 0,
        "eccAnom": 0,
        "meanAnom": 0
      },
      "position": {
        "x": 3.1779584437873818e-18,
        "y": 0.051828872853762385,
        "z": 0.002716236129008785
      },
      "velocity": {
        "x": -32.52537174763376,
        "y": 1.9888751951764076e-15,
        "z": 1.0423253225032065e-16
      },
      "nonStellarProceduralManifestation": true,
      "atmosphere": "orange"
    }
  ],
  "particlesConfiguration": {
    "max": 50000,
    "softening": 0,
    "size": 80,
    "shapes": []
  },
  "ringToBeAdded": {
    "primary": "WASP-79",
    "a": 0,
    "aInterval": 0,
    "i": 0,
    "lAn": 0,
    "number": 1000,
    "size": 0,
    "ringsAreBeingAdded": false
  }
}
