{
  "name": "HD 208487 - System",
  "description": "HD 208487 is a Sun-like G/F-type star with 1 known planet. Planet positions and surfaces are procedurally generated. Data from the NASA Exoplanet Archive.",
  "playing": false,
  "isLoaded": false,
  "elapsedTime": 0,
  "collisions": true,
  "massBeingModified": {
    "name": "HD 208487",
    "unitName": "Solar Units",
    "unitMassQuantity": 1.15,
    "m": 1.15
  },
  "category": {
    "name": "Exoplanets",
    "subCategory": "1-Planet System"
  },
  "camera": {
    "cameraFocus": "HD 208487",
    "logarithmicDepthBuffer": false,
    "rotatingReferenceFrame": "HD 208487"
  },
  "integrator": {
    "name": "RK4",
    "g": 39.5,
    "dt": 0.0001,
    "tol": 0.0001,
    "maxDt": 0.001,
    "minDt": 0.000001,
    "useBarnesHut": false,
    "theta": 0.5,
    "softeningConstant": 0
  },
  "barycenter": {
    "display": false,
    "barycenterMassOne": "HD 208487",
    "barycenterMassTwo": "HD 208487 b",
    "systemBarycenter": true
  },
  "graphics": {
    "background": true,
    "orbits": true,
    "habitableZone": true,
    "trails": true,
    "labels": true
  },
  "masses": [
    {
      "name": "HD 208487",
      "type": "star",
      "m": 1.15,
      "radius": 11913.2,
      "tilt": 0,
      "temperature": 6134,
      "graphics": {
        "orbit": true,
        "trail": true,
        "label": true
      },
      "elements": {
        "a": 0,
        "e": 0,
        "i": 0,
        "argP": 0,
        "lAn": 0,
        "eccAnom": 0
      },
      "position": {
        "x": 0,
        "y": 0,
        "z": 0
      },
      "velocity": {
        "x": 0.004643959897767283,
        "y": -0.0023629729378894684,
        "z": -0.0001238381641807107
      },
      "nonStellarProceduralManifestation": false
    },
    {
      "name": "HD 208487 b",
      "type": "gas giant planet",
      "m": 0.00043904180486166,
      "radius": 1344.3268,
      "tilt": 0,
      "graphics": {
        "orbit": true,
        "trail": true,
        "label": true
      },
      "elements": {
        "a": 0,
        "e": 0,
        "i": 0,
        "argP": 0,
        "lAn": 0,
        "trueAnom": 0,
        "eccAnom": 0,
        "meanAnom": 0
      },
      "position": {
        "x": 0.1515874278630347,
        "y": 0.2970993553152443,
        "z": 0.015570317438495157
      },
      "velocity": {
        "x": -12.16411244508973,
        "y": 6.189430820668966,
        "z": 0.32437432433727176
      },
      "nonStellarProceduralManifestation": true,
      "atmosphere": "beige"
    }
  ],
  "particlesConfiguration": {
    "max": 50000,
    "softening": 0,
    "size": 80,
    "shapes": []
  },
  "ringToBeAdded": {
    "primary": "HD 208487",
    "a": 0,
    "aInterval": 0,
    "i": 0,
    "lAn": 0,
    "number": 1000,
    "size": 0,
    "ringsAreBeingAdded": false
  }
}
